sncf_api/__init__.py
sncf_api/sncf_api.py
sncf_api/sncf_api_tester.py
sncf_api-0.1.1.dist-info/WHEEL
sncf_api-0.1.1.dist-info/METADATA
sncf_api-0.1.1.dist-info/RECORD
