Metadata-Version: 2.1
Name: sncf-api
Version: 0.1.1
Summary: A class of functions that can call the different SNCF API's from https://data.sncf.com/, returns data as pandas dataframe or .json() object.
Home-page: https://github.com/matthew73210/sncf_api
License: MIT
Keywords: python,SNCF,poetry
Author: Matthew Burton
Author-email: matthewmaxwellburton@gmail.com
Requires-Python: >=3.8,<4.0
Classifier: License :: OSI Approved :: MIT License
Classifier: Programming Language :: Python :: 3
Classifier: Programming Language :: Python :: 3.8
Requires-Dist: pandas (>=1.0.3,<2.0.0)
Requires-Dist: requests (>=2.23.0,<3.0.0)
Project-URL: Repository, https://github.com/matthew73210/sncf_api
